merkle_tree/__init__.py
merkle_tree/hasher.py
merkle_tree/protocols.py
merkle_tree/py.typed
lokryn_merkle_tree-0.1.0.dist-info/METADATA
lokryn_merkle_tree-0.1.0.dist-info/WHEEL
lokryn_merkle_tree-0.1.0.dist-info/licenses/LICENSE
lokryn_merkle_tree-0.1.0.dist-info/RECORD
