Metadata-Version: 2.4
Name: lokryn-merkle-tree
Version: 0.1.0
Summary: Merkle tree and hash chain utilities for immutable audit logs
Project-URL: Homepage, https://github.com/lokryn-llc/merkle-tree
Project-URL: Repository, https://github.com/lokryn-llc/merkle-tree
Project-URL: Documentation, https://github.com/lokryn-llc/merkle-tree#readme
Project-URL: Issues, https://github.com/lokryn-llc/merkle-tree/issues
Author-email: daniel-wallace-personal <wallace.danielk@gmail.com>
License-Expression: AGPL-3.0-only
License-File: LICENSE
Keywords: audit-log,cryptography,hash-chain,integrity,merkle
Classifier: Development Status :: 4 - Beta
Classifier: Intended Audience :: Developers
Classifier: License :: OSI Approved :: GNU Affero General Public License v3
Classifier: Programming Language :: Python :: 3
Classifier: Programming Language :: Python :: 3.12
Classifier: Programming Language :: Python :: 3.13
Classifier: Topic :: Security :: Cryptography
Classifier: Topic :: Software Development :: Libraries :: Python Modules
Classifier: Typing :: Typed
Requires-Python: >=3.12
